LICENSE.txt
MANIFEST.in
README.md
setup.py
tsr/__init__.py
tsr/cl.py
tsr.egg-info/PKG-INFO
tsr.egg-info/SOURCES.txt
tsr.egg-info/dependency_links.txt
tsr.egg-info/entry_points.txt
tsr.egg-info/requires.txt
tsr.egg-info/top_level.txt
tsr/classes/__init__.py
tsr/classes/forum_page.py
tsr/modules/__init__.py
tsr/modules/colours.py
tsr/modules/forumload.py
tsr/modules/general.py
tsr/modules/generate_forums.py
tsr/modules/grammar.py
tsr/modules/os_info.py
tsr/modules/regex.py
tsr/modules/scrapers.py
tsr/modules/soups.py
tsr/modules/__pycache__/__init__.cpython-36.pyc
tsr/modules/__pycache__/colours.cpython-36.pyc
tsr/modules/__pycache__/forumload.cpython-36.pyc
tsr/modules/__pycache__/general.cpython-36.pyc
tsr/modules/__pycache__/grammar.cpython-36.pyc
tsr/modules/__pycache__/os_info.cpython-36.pyc
tsr/modules/__pycache__/regex.cpython-36.pyc
tsr/modules/__pycache__/scrapers.cpython-36.pyc
tsr/modules/__pycache__/soups.cpython-36.pyc
tsr/settings/.commands.json.swp
tsr/settings/colours_domains.json
tsr/settings/colours_regex.json
tsr/settings/colours_words.json
tsr/settings/commands.json
tsr/settings/credentials.json
tsr/settings/forums.json
tsr/settings/paths.json
tsr/settings/settings.json
tsr/settings/username_to_id.json
tsr/settings/users.json
tsr/spiders/searchAPI.py
tsr/spiders/__pycache__/searchAPI.cpython-36.pyc